cassavapy/__init__.py
cassavapy/API/__init__.py
cassavapy/API/create.py
cassavapy/API/extract.py
cassavapy/API/irrigation.py
cassavapy/API/run.py
cassavapy/create/__init__.py
cassavapy/create/classes.py
cassavapy/create/exp_functions.py
cassavapy/create/filex.py
cassavapy/create/soil.py
cassavapy/create/write_functions.py
cassavapy/outputs/Experimental.py
cassavapy/outputs/Seasonal.py
cassavapy/outputs/__init__.py
cassavapy/outputs/output.py
cassavapy/run/__init__.py
cassavapy/run/batch.py
tests/__init__.py
tests/test_exp.py
tests/test_file.py
tests/utils.py
CassavaPy-0.0.13.dist-info/METADATA
CassavaPy-0.0.13.dist-info/WHEEL
CassavaPy-0.0.13.dist-info/top_level.txt
CassavaPy-0.0.13.dist-info/RECORD
