Metadata-Version: 2.1
Name: CassavaPy
Version: 0.0.13
Summary: A package to write, run and get outputs from DSSAT-Manihot model
Home-page: https://github.com/FabioSeixas/CassavaPy
Author: Fábio Seixas
Author-email: flscosta94@gmail.com
License: UNKNOWN
Platform: UNKNOWN
Classifier: Programming Language :: Python :: 3
Classifier: License :: OSI Approved :: MIT License
Classifier: Operating System :: OS Independent
Requires-Python: >=3.8
Requires-Dist: numpy (>=1.18.0)
Requires-Dist: pandas (>=0.25.3)
